llmify/__init__.py
llmify/cli.py
llmify/generate_llmstxt.py
llmify_cli-0.1.6.dist-info/licenses/LICENSE
llmify_cli-0.1.6.dist-info/METADATA
llmify_cli-0.1.6.dist-info/WHEEL
llmify_cli-0.1.6.dist-info/entry_points.txt
llmify_cli-0.1.6.dist-info/top_level.txt
llmify_cli-0.1.6.dist-info/RECORD
