Metadata-Version: 2.4
Name: llmify-cli
Version: 0.1.6
Summary: LLM-ify: create LLM-ready markdown and text from websites.
Author: Chillbruhhh
License: PolyForm Noncommercial License 1.0.0
Project-URL: Homepage, https://github.com/Chillbruhhh/LLM-ify
Requires-Python: >=3.8
License-File: LICENSE
Requires-Dist: openai>=1.3.0
Requires-Dist: python-dotenv>=1.0.0
Requires-Dist: crawl4ai>=0.7.0
Requires-Dist: windows-curses>=2.3.0; platform_system == "Windows"
Dynamic: license-file
